_Clothoids.cpython-312-darwin.so
Clothoids.py
clothoids-2.0.33.dist-info/RECORD
clothoids-2.0.33.dist-info/WHEEL
clothoids-2.0.33.dist-info/top_level.txt
clothoids-2.0.33.dist-info/METADATA
clothoids-2.0.33.dist-info/licenses/LICENSE
