Metadata-Version: 2.1
Name: Clothoids
Version: 2.0.33
Summary: G1 and G2 fitting with clothoids, spline of clothoids, circle arc and biarc.
Author: Enrico Bertolazzi
License-File: LICENSE
